odoo/addons/stock_picking_operation_manual_lot_selection/README.rst
odoo/addons/stock_picking_operation_manual_lot_selection/__init__.py
odoo/addons/stock_picking_operation_manual_lot_selection/__manifest__.py
odoo/addons/stock_picking_operation_manual_lot_selection/i18n/en_US.po
odoo/addons/stock_picking_operation_manual_lot_selection/i18n/fr.po
odoo/addons/stock_picking_operation_manual_lot_selection/i18n/stock_picking_operation_manual_lot_selection.pot
odoo/addons/stock_picking_operation_manual_lot_selection/models/__init__.py
odoo/addons/stock_picking_operation_manual_lot_selection/models/stock_move_line.py
odoo/addons/stock_picking_operation_manual_lot_selection/models/stock_picking.py
odoo/addons/stock_picking_operation_manual_lot_selection/readme/AUTHORS.rst
odoo/addons/stock_picking_operation_manual_lot_selection/readme/CONFIGURE.rst
odoo/addons/stock_picking_operation_manual_lot_selection/readme/CONTRIBUTORS.rst
odoo/addons/stock_picking_operation_manual_lot_selection/readme/DESCRIPTION.rst
odoo/addons/stock_picking_operation_manual_lot_selection/readme/USAGE.rst
odoo/addons/stock_picking_operation_manual_lot_selection/static/description/icon.png
odoo/addons/stock_picking_operation_manual_lot_selection/static/description/index.html
odoo/addons/stock_picking_operation_manual_lot_selection/tests/__init__.py
odoo/addons/stock_picking_operation_manual_lot_selection/tests/test_stock_picking_lot.py
odoo/addons/stock_picking_operation_manual_lot_selection/views/stock_move_views.xml
odoo/addons/stock_picking_operation_manual_lot_selection/views/stock_picking_views.xml
odoo_addon_stock_picking_operation_manual_lot_selection-15.0.1.0.0.2.dist-info/METADATA
odoo_addon_stock_picking_operation_manual_lot_selection-15.0.1.0.0.2.dist-info/WHEEL
odoo_addon_stock_picking_operation_manual_lot_selection-15.0.1.0.0.2.dist-info/top_level.txt
odoo_addon_stock_picking_operation_manual_lot_selection-15.0.1.0.0.2.dist-info/RECORD
